enthusiast_file_parsers/__init__.py
enthusiast_file_parsers/image.py
enthusiast_file_parsers/pdf.py
enthusiast_file_parsers/text.py
enthusiast_file_parsers-1.0.0.dist-info/METADATA
enthusiast_file_parsers-1.0.0.dist-info/WHEEL
enthusiast_file_parsers-1.0.0.dist-info/RECORD
